{
    "opml": {
        "head": {
            "title": "Jacobr tweets",
            "dateCreated": "Sun, 30 Jan 2022 14:59:22 GMT",
            "expansionState": "1,2",
            "urlPublic": "http://tweets.opml.org/Jacobr/tweets.opml",
            "urlUpdateSocket": "ws://tweets.opml.org:1481/",
            "dateModified": "Sat, 02 Jul 2022 22:41:38 GMT"
        },
        "body": {
            "subs": [
                {
                    "text": "July 2022",
                    "type": "calendarMonth",
                    "name": "july2022",
                    "subs": [
                        {
                            "text": "July 2",
                            "type": "calendarDay",
                            "name": "02",
                            "subs": [
                                {
                                    "text": "@Kamali_Thompson Only $5?",
                                    "rawText": "@Kamali_Thompson Only $5?",
                                    "type": "tweet",
                                    "created": "Sat, 02 Jul 2022 22:34:40 GMT",
                                    "tweetId": "1543362549558972417",
                                    "urltweet": "https://twitter.com/Jacobr/status/1543362549558972417",
                                    "inReplyToId": "1543241168334602241",
                                    "tweetUserName": "Jacobr"
                                }
                            ]
                        },
                        {
                            "text": "July 1",
                            "type": "calendarDay",
                            "name": "01",
                            "subs": [
                                {
                                    "text": "@mreider @mreider has an opinion.  Just an idea - not prohibition.  When deleted user stories breed a second life, just sing reincarnation songs and be happy for them!? In a forever backlog, just attach the reincarnation to its grandparent - leaving them forever at priority 99 together ..",
                                    "rawText": "@mreider @mreider has an opinion.  Just an idea - not prohibition.  When deleted user stories breed a second life, just sing reincarnation songs and be happy for them!? In a forever backlog, just attach the reincarnation to its grandparent - leaving them forever at priority 99 together ..",
                                    "type": "tweet",
                                    "created": "Fri, 01 Jul 2022 22:45:10 GMT",
                                    "tweetId": "1543002804452823045",
                                    "urltweet": "https://twitter.com/Jacobr/status/1543002804452823045",
                                    "inReplyToId": "1540270846425563137",
                                    "tweetUserName": "Jacobr"
                                },
                                {
                                    "text": "@mreider Priority = 99. Gotta leave them in the backlog or they'll come back again and you'll go through the effort again.",
                                    "rawText": "@mreider Priority = 99. Gotta leave them in the backlog or they'll come back again and you'll go through the effort again.",
                                    "type": "tweet",
                                    "created": "Fri, 01 Jul 2022 14:34:04 GMT",
                                    "tweetId": "1542879213094682627",
                                    "urltweet": "https://twitter.com/Jacobr/status/1542879213094682627",
                                    "inReplyToId": "1542841267264131073",
                                    "tweetUserName": "Jacobr"
                                }
                            ]
                        }
                    ]
                }
            ]
        }
    }
}