{
    "opml": {
        "head": {
            "title": "DevHawk tweets",
            "dateCreated": "Mon, 20 Dec 2021 21:35:30 GMT",
            "expansionState": "1,2",
            "urlPublic": "http://tweets.opml.org/DevHawk/tweets.opml",
            "urlUpdateSocket": "ws://tweets.opml.org:1481/",
            "dateModified": "Sat, 26 Mar 2022 04:39:07 GMT"
        },
        "body": {
            "subs": [
                {
                    "text": "March 2022",
                    "type": "calendarMonth",
                    "name": "march2022",
                    "subs": [
                        {
                            "text": "March 26",
                            "type": "calendarDay",
                            "name": "26",
                            "subs": [
                                {
                                    "text": "Tonight, we got to see my youngest in his high school's production of Chicago. He plays Amos and did a fantastic job with \"Mr. Cellophane\".\n\nI might be slightly biased.\n\nEver so slightly biased. <a href=\"https://t.co/gOXBRLVLEA\">[link]</a>",
                                    "rawText": "Tonight, we got to see my youngest in his high school's production of Chicago. He plays Amos and did a fantastic job with \"Mr. Cellophane\".\n\nI might be slightly biased.\n\nEver so slightly biased. https://t.co/gOXBRLVLEA",
                                    "type": "tweet",
                                    "created": "Sat, 26 Mar 2022 04:36:13 GMT",
                                    "tweetId": "1507577138827784194",
                                    "urltweet": "https://twitter.com/DevHawk/status/1507577138827784194",
                                    "tweetUserName": "DevHawk"
                                }
                            ]
                        },
                        {
                            "text": "March 24",
                            "type": "calendarDay",
                            "name": "24",
                            "subs": [
                                {
                                    "text": "Holy fuck, I didn't realize Michelle Yeoh's husband in Everything Everywhere All at Once is fucking Short Round all grown up.\n\nTrailer looks fantastic. The reviews are phenomenal. The genre is right in my wheelhouse. Ke Huy Quan is the cherry on top.\n\nCAN NOT WAIT TO SEE THIS <a href=\"https://t.co/BkS5hmDhQS\">[link]</a>",
                                    "rawText": "Holy fuck, I didn't realize Michelle Yeoh's husband in Everything Everywhere All at Once is fucking Short Round all grown up.\n\nTrailer looks fantastic. The reviews are phenomenal. The genre is right in my wheelhouse. Ke Huy Quan is the cherry on top.\n\nCAN NOT WAIT TO SEE THIS https://t.co/BkS5hmDhQS",
                                    "type": "tweet",
                                    "created": "Thu, 24 Mar 2022 22:02:02 GMT",
                                    "tweetId": "1507115548659707919",
                                    "urltweet": "https://twitter.com/DevHawk/status/1507115548659707919",
                                    "tweetUserName": "DevHawk"
                                }
                            ]
                        },
                        {
                            "text": "March 22",
                            "type": "calendarDay",
                            "name": "22",
                            "subs": [
                                {
                                    "text": "@neow3j @roschler @ax_labs Honestly, Salem is probably more of a neo-python user since my youngest son has a pet snake 🐍",
                                    "rawText": "@neow3j @roschler @ax_labs Honestly, Salem is probably more of a neo-python user since my youngest son has a pet snake 🐍",
                                    "type": "tweet",
                                    "created": "Tue, 22 Mar 2022 22:31:33 GMT",
                                    "tweetId": "1506398200181112833",
                                    "urltweet": "https://twitter.com/DevHawk/status/1506398200181112833",
                                    "inReplyToId": "1506375985926709253",
                                    "tweetUserName": "DevHawk"
                                },
                                {
                                    "text": "I usually don't post personal pictures, but I really dug how this picture of our cat Salem came out. <a href=\"https://t.co/rnTZkW3VHf\">[link]</a>",
                                    "rawText": "I usually don't post personal pictures, but I really dug how this picture of our cat Salem came out. https://t.co/rnTZkW3VHf",
                                    "type": "tweet",
                                    "created": "Tue, 22 Mar 2022 17:45:54 GMT",
                                    "tweetId": "1506326315011436549",
                                    "urltweet": "https://twitter.com/DevHawk/status/1506326315011436549",
                                    "tweetUserName": "DevHawk"
                                }
                            ]
                        },
                        {
                            "text": "March 20",
                            "type": "calendarDay",
                            "name": "20",
                            "subs": [
                                {
                                    "text": "Its a crime that don't get a new @NeillBlomkamp movie every year or two.",
                                    "rawText": "Its a crime that don't get a new @NeillBlomkamp movie every year or two.",
                                    "type": "tweet",
                                    "created": "Sun, 20 Mar 2022 05:06:59 GMT",
                                    "tweetId": "1505410551236612096",
                                    "urltweet": "https://twitter.com/DevHawk/status/1505410551236612096",
                                    "tweetUserName": "DevHawk"
                                }
                            ]
                        },
                        {
                            "text": "March 17",
                            "type": "calendarDay",
                            "name": "17",
                            "subs": [
                                {
                                    "text": "Minor update to @Neo_Blockchain Smart Contract Debugger preview published. Watch Window expression evaluation now leverages type information. Now can watch specific struct fields or specific list/map items. Compound expressions also supported, as shown in this screenshot <a href=\"https://t.co/Gg1Ou6eIYp\">[link]</a>",
                                    "rawText": "Minor update to @Neo_Blockchain Smart Contract Debugger preview published. Watch Window expression evaluation now leverages type information. Now can watch specific struct fields or specific list/map items. Compound expressions also supported, as shown in this screenshot https://t.co/Gg1Ou6eIYp",
                                    "type": "tweet",
                                    "created": "Thu, 17 Mar 2022 18:00:50 GMT",
                                    "tweetId": "1504518135184977922",
                                    "urltweet": "https://twitter.com/DevHawk/status/1504518135184977922",
                                    "tweetUserName": "DevHawk"
                                }
                            ]
                        },
                        {
                            "text": "March 16",
                            "type": "calendarDay",
                            "name": "16",
                            "subs": [
                                {
                                    "text": "@roschler @john_devadoss <a href=\"https://t.co/iRRw9WWraE\">[link]</a>",
                                    "rawText": "@roschler @john_devadoss https://t.co/iRRw9WWraE",
                                    "type": "tweet",
                                    "created": "Wed, 16 Mar 2022 13:28:45 GMT",
                                    "tweetId": "1504087273842782208",
                                    "urltweet": "https://twitter.com/DevHawk/status/1504087273842782208",
                                    "inReplyToId": "1503786442010636288",
                                    "tweetUserName": "DevHawk"
                                }
                            ]
                        },
                        {
                            "text": "March 15",
                            "type": "calendarDay",
                            "name": "15",
                            "subs": [
                                {
                                    "text": "For @Neo_Blockchain developers wanting to try out the new Storage Schema preview, I've posted more detailed getting started instructions <a href=\"https://t.co/VTZWtD6Wz2\">[link]</a>",
                                    "rawText": "For @Neo_Blockchain developers wanting to try out the new Storage Schema preview, I've posted more detailed getting started instructions https://t.co/VTZWtD6Wz2",
                                    "type": "tweet",
                                    "created": "Tue, 15 Mar 2022 21:33:18 GMT",
                                    "tweetId": "1503846827547799552",
                                    "urltweet": "https://twitter.com/DevHawk/status/1503846827547799552",
                                    "tweetUserName": "DevHawk"
                                }
                            ]
                        },
                        {
                            "text": "March 14",
                            "type": "calendarDay",
                            "name": "14",
                            "subs": [
                                {
                                    "text": "We just shipped a major update to the #NeoBlockchainToolkit Smart Contract Debugger today. It's not completely baked yet, so we are shipping it as a preview.\n\nLet me tell you why running the preview is TOTALLY worth it. (1/20)",
                                    "rawText": "We just shipped a major update to the #NeoBlockchainToolkit Smart Contract Debugger today. It's not completely baked yet, so we are shipping it as a preview.\n\nLet me tell you why running the preview is TOTALLY worth it. (1/20)",
                                    "type": "tweet",
                                    "created": "Mon, 14 Mar 2022 22:59:02 GMT",
                                    "tweetId": "1503506015337164803",
                                    "urltweet": "https://twitter.com/DevHawk/status/1503506015337164803",
                                    "tweetUserName": "DevHawk",
                                    "subs": [
                                        {
                                            "text": "A few weeks ago, I started working on improving the developer experience for contract storage in the debugger. Every Neo contract has its own \"private\" key/value store where it can persist data it needs to do its job. Fungible token balances, NFT details, stuff like that. (2/20)",
                                            "rawText": "A few weeks ago, I started working on improving the developer experience for contract storage in the debugger. Every Neo contract has its own \"private\" key/value store where it can persist data it needs to do its job. Fungible token balances, NFT details, stuff like that. (2/20)",
                                            "type": "tweet",
                                            "created": "Mon, 14 Mar 2022 22:59:02 GMT",
                                            "tweetId": "1503506017140629511",
                                            "urltweet": "https://twitter.com/DevHawk/status/1503506017140629511",
                                            "inReplyToId": "1503506015337164803",
                                            "tweetUserName": "DevHawk",
                                            "subs": [
                                                {
                                                    "text": "Note, \"private\" in quotes because no data on the blockchain is private. A core point of blockchain is to publish a publicly visible cryptographically authenticated record. But contract data is only visible from outside and only the contract can modify its key/value store. (3/20)",
                                                    "rawText": "Note, \"private\" in quotes because no data on the blockchain is private. A core point of blockchain is to publish a publicly visible cryptographically authenticated record. But contract data is only visible from outside and only the contract can modify its key/value store. (3/20)",
                                                    "type": "tweet",
                                                    "created": "Mon, 14 Mar 2022 22:59:03 GMT",
                                                    "tweetId": "1503506018881265670",
                                                    "urltweet": "https://twitter.com/DevHawk/status/1503506018881265670",
                                                    "inReplyToId": "1503506017140629511",
                                                    "tweetUserName": "DevHawk",
                                                    "subs": [
                                                        {
                                                            "text": "Anyway, key/value data stores are simple and flexible, but they are a pain to inspect. The key and value are just streams of bytes. And that's how the Neo Contract Debugger has traditionally displayed contract storage. An accurate view, but not a useful or productive view. (4/20) <a href=\"https://t.co/KRqGnHkrRA\">[link]</a>",
                                                            "rawText": "Anyway, key/value data stores are simple and flexible, but they are a pain to inspect. The key and value are just streams of bytes. And that's how the Neo Contract Debugger has traditionally displayed contract storage. An accurate view, but not a useful or productive view. (4/20) https://t.co/KRqGnHkrRA",
                                                            "type": "tweet",
                                                            "created": "Mon, 14 Mar 2022 22:59:04 GMT",
                                                            "tweetId": "1503506023532822532",
                                                            "urltweet": "https://twitter.com/DevHawk/status/1503506023532822532",
                                                            "inReplyToId": "1503506018881265670",
                                                            "tweetUserName": "DevHawk",
                                                            "subs": [
                                                                {
                                                                    "text": "Contract storage *is* structured - even if the structure isn't visible at the storage layer. Keys typically have a constant prefix followed by zero or more typed key segments. Values are also consistently typed. (5/20)",
                                                                    "rawText": "Contract storage *is* structured - even if the structure isn't visible at the storage layer. Keys typically have a constant prefix followed by zero or more typed key segments. Values are also consistently typed. (5/20)",
                                                                    "type": "tweet",
                                                                    "created": "Mon, 14 Mar 2022 22:59:04 GMT",
                                                                    "tweetId": "1503506025659338752",
                                                                    "urltweet": "https://twitter.com/DevHawk/status/1503506025659338752",
                                                                    "inReplyToId": "1503506023532822532",
                                                                    "tweetUserName": "DevHawk",
                                                                    "subs": [
                                                                        {
                                                                            "text": "For example: a fungible token might store token balances as integers with a constant prefix + user's address as the key. An NFT key/value pair might store information about a specific token (name, URL, owner, etc.) in a serialized structure keyed to token's unique ID. (6/20)",
                                                                            "rawText": "For example: a fungible token might store token balances as integers with a constant prefix + user's address as the key. An NFT key/value pair might store information about a specific token (name, URL, owner, etc.) in a serialized structure keyed to token's unique ID. (6/20)",
                                                                            "type": "tweet",
                                                                            "created": "Mon, 14 Mar 2022 22:59:05 GMT",
                                                                            "tweetId": "1503506027370582017",
                                                                            "urltweet": "https://twitter.com/DevHawk/status/1503506027370582017",
                                                                            "inReplyToId": "1503506025659338752",
                                                                            "tweetUserName": "DevHawk",
                                                                            "subs": [
                                                                                {
                                                                                    "text": "I set out to provide what @roschler called \"deep inspection\" of contract storage. I wanted the debugger to automatically decode each key segment and the value, giving the developer a logical view of storage with types rather than the physical view of raw bytes. (7/20)",
                                                                                    "rawText": "I set out to provide what @roschler called \"deep inspection\" of contract storage. I wanted the debugger to automatically decode each key segment and the value, giving the developer a logical view of storage with types rather than the physical view of raw bytes. (7/20)",
                                                                                    "type": "tweet",
                                                                                    "created": "Mon, 14 Mar 2022 22:59:05 GMT",
                                                                                    "tweetId": "1503506029023154176",
                                                                                    "urltweet": "https://twitter.com/DevHawk/status/1503506029023154176",
                                                                                    "inReplyToId": "1503506027370582017",
                                                                                    "tweetUserName": "DevHawk",
                                                                                    "subs": [
                                                                                        {
                                                                                            "text": "We actually shipped the first preview of \"Storage Schema\" about a week ago. I didn't make much noise at the time because I wasn't satisfied. The deep inspection experience worked but required the developer to specify the schema information by hand. (8/20)",
                                                                                            "rawText": "We actually shipped the first preview of \"Storage Schema\" about a week ago. I didn't make much noise at the time because I wasn't satisfied. The deep inspection experience worked but required the developer to specify the schema information by hand. (8/20)",
                                                                                            "type": "tweet",
                                                                                            "created": "Mon, 14 Mar 2022 22:59:06 GMT",
                                                                                            "tweetId": "1503506030809939969",
                                                                                            "urltweet": "https://twitter.com/DevHawk/status/1503506030809939969",
                                                                                            "inReplyToId": "1503506029023154176",
                                                                                            "tweetUserName": "DevHawk",
                                                                                            "subs": [
                                                                                                {
                                                                                                    "text": "Writing JSON by hand to describe a contract's storage schema was fine for a proof of concept. However, I wanted tools to generate the schema information automatically. So I started updating the Neo C# compiler. \n\nThat's when things got ... interesting. (9/20)",
                                                                                                    "rawText": "Writing JSON by hand to describe a contract's storage schema was fine for a proof of concept. However, I wanted tools to generate the schema information automatically. So I started updating the Neo C# compiler. \n\nThat's when things got ... interesting. (9/20)",
                                                                                                    "type": "tweet",
                                                                                                    "created": "Mon, 14 Mar 2022 22:59:06 GMT",
                                                                                                    "tweetId": "1503506032726720514",
                                                                                                    "urltweet": "https://twitter.com/DevHawk/status/1503506032726720514",
                                                                                                    "inReplyToId": "1503506030809939969",
                                                                                                    "tweetUserName": "DevHawk",
                                                                                                    "subs": [
                                                                                                        {
                                                                                                            "text": "Neo contracts are written in mainstream programming languages such as C#, Java and Python but run on the Neo virtual machine. There are compilers from various parts of the Neo community for each of these languages that emit Neo VM bytecode - including the Neo C# compiler. (10/20)",
                                                                                                            "rawText": "Neo contracts are written in mainstream programming languages such as C#, Java and Python but run on the Neo virtual machine. There are compilers from various parts of the Neo community for each of these languages that emit Neo VM bytecode - including the Neo C# compiler. (10/20)",
                                                                                                            "type": "tweet",
                                                                                                            "created": "Mon, 14 Mar 2022 22:59:07 GMT",
                                                                                                            "tweetId": "1503506034429636608",
                                                                                                            "urltweet": "https://twitter.com/DevHawk/status/1503506034429636608",
                                                                                                            "inReplyToId": "1503506032726720514",
                                                                                                            "tweetUserName": "DevHawk",
                                                                                                            "subs": [
                                                                                                                {
                                                                                                                    "text": "The original Neo Legacy C# compiler translated .NET IL to Neo VM byte code. For Neo N3, @neoerikzhang wrote a new compiler that works directly against C# source using Roslyn.\n\nThis turned out to be serendipitous for my Storage Schema efforts. (11/20)",
                                                                                                                    "rawText": "The original Neo Legacy C# compiler translated .NET IL to Neo VM byte code. For Neo N3, @neoerikzhang wrote a new compiler that works directly against C# source using Roslyn.\n\nThis turned out to be serendipitous for my Storage Schema efforts. (11/20)",
                                                                                                                    "type": "tweet",
                                                                                                                    "created": "Mon, 14 Mar 2022 22:59:07 GMT",
                                                                                                                    "tweetId": "1503506036346724352",
                                                                                                                    "urltweet": "https://twitter.com/DevHawk/status/1503506036346724352",
                                                                                                                    "inReplyToId": "1503506034429636608",
                                                                                                                    "tweetUserName": "DevHawk",
                                                                                                                    "subs": [
                                                                                                                        {
                                                                                                                            "text": "The type model used to describe *storage* types could also describe *runtime* types as well! With the Roslyn based compiler, all the rich C# semantic information was readily available.\n\nUpdating the compiler to emit runtime type information was pretty straightforward. (12/20)",
                                                                                                                            "rawText": "The type model used to describe *storage* types could also describe *runtime* types as well! With the Roslyn based compiler, all the rich C# semantic information was readily available.\n\nUpdating the compiler to emit runtime type information was pretty straightforward. (12/20)",
                                                                                                                            "type": "tweet",
                                                                                                                            "created": "Mon, 14 Mar 2022 22:59:07 GMT",
                                                                                                                            "tweetId": "1503506038019919873",
                                                                                                                            "urltweet": "https://twitter.com/DevHawk/status/1503506038019919873",
                                                                                                                            "inReplyToId": "1503506036346724352",
                                                                                                                            "tweetUserName": "DevHawk",
                                                                                                                            "subs": [
                                                                                                                                {
                                                                                                                                    "text": "Automatically generating storage type info was *harder* than runtime type info! \n\nStorage schema of a C# Neo contract is done with imperative code. I didn't try to reverse engineer storage schema from C# source. I added custom attributes to capture storage schema instead. (13/20)",
                                                                                                                                    "rawText": "Automatically generating storage type info was *harder* than runtime type info! \n\nStorage schema of a C# Neo contract is done with imperative code. I didn't try to reverse engineer storage schema from C# source. I added custom attributes to capture storage schema instead. (13/20)",
                                                                                                                                    "type": "tweet",
                                                                                                                                    "created": "Mon, 14 Mar 2022 22:59:08 GMT",
                                                                                                                                    "tweetId": "1503506039706058753",
                                                                                                                                    "urltweet": "https://twitter.com/DevHawk/status/1503506039706058753",
                                                                                                                                    "inReplyToId": "1503506038019919873",
                                                                                                                                    "tweetUserName": "DevHawk",
                                                                                                                                    "subs": [
                                                                                                                                        {
                                                                                                                                            "text": "Here's what the new Storage Schema attributes look like in action: (14/20) <a href=\"https://t.co/U6KsT3Edm4\">[link]</a>",
                                                                                                                                            "rawText": "Here's what the new Storage Schema attributes look like in action: (14/20) https://t.co/U6KsT3Edm4",
                                                                                                                                            "type": "tweet",
                                                                                                                                            "created": "Mon, 14 Mar 2022 22:59:09 GMT",
                                                                                                                                            "tweetId": "1503506043531567104",
                                                                                                                                            "urltweet": "https://twitter.com/DevHawk/status/1503506043531567104",
                                                                                                                                            "inReplyToId": "1503506039706058753",
                                                                                                                                            "tweetUserName": "DevHawk",
                                                                                                                                            "subs": [
                                                                                                                                                {
                                                                                                                                                    "text": "This attribute-based approach is very much a first draft. It's simple and it works, but I'm not convinced it's the best approach. We are shipping this update as a preview so we can iterate and get feedback on the design. (15/20)",
                                                                                                                                                    "rawText": "This attribute-based approach is very much a first draft. It's simple and it works, but I'm not convinced it's the best approach. We are shipping this update as a preview so we can iterate and get feedback on the design. (15/20)",
                                                                                                                                                    "type": "tweet",
                                                                                                                                                    "created": "Mon, 14 Mar 2022 22:59:09 GMT",
                                                                                                                                                    "tweetId": "1503506045628346371",
                                                                                                                                                    "urltweet": "https://twitter.com/DevHawk/status/1503506045628346371",
                                                                                                                                                    "inReplyToId": "1503506043531567104",
                                                                                                                                                    "tweetUserName": "DevHawk",
                                                                                                                                                    "subs": [
                                                                                                                                                        {
                                                                                                                                                            "text": "There is also a sample contract where you can see the new experience in action. Install preview debugger, clone, build and run...err, debug.\n\nThis link will get you started: <a href=\"https://t.co/2ygtod7Lv2\">[link]</a> (16/20)",
                                                                                                                                                            "rawText": "There is also a sample contract where you can see the new experience in action. Install preview debugger, clone, build and run...err, debug.\n\nThis link will get you started: https://t.co/2ygtod7Lv2 (16/20)",
                                                                                                                                                            "type": "tweet",
                                                                                                                                                            "created": "Mon, 14 Mar 2022 22:59:10 GMT",
                                                                                                                                                            "tweetId": "1503506047327084546",
                                                                                                                                                            "urltweet": "https://twitter.com/DevHawk/status/1503506047327084546",
                                                                                                                                                            "inReplyToId": "1503506045628346371",
                                                                                                                                                            "tweetUserName": "DevHawk",
                                                                                                                                                            "subs": [
                                                                                                                                                                {
                                                                                                                                                                    "text": "Here's a screen shot of the same contract's variables window from earlier in the thread, but now using the Neo Debugger Preview.\n\nI like to think this is a dramatic improvement over looking at raw byte streams! (17/20) <a href=\"https://t.co/HXbe57nZiQ\">[link]</a>",
                                                                                                                                                                    "rawText": "Here's a screen shot of the same contract's variables window from earlier in the thread, but now using the Neo Debugger Preview.\n\nI like to think this is a dramatic improvement over looking at raw byte streams! (17/20) https://t.co/HXbe57nZiQ",
                                                                                                                                                                    "type": "tweet",
                                                                                                                                                                    "created": "Mon, 14 Mar 2022 22:59:11 GMT",
                                                                                                                                                                    "tweetId": "1503506051668140032",
                                                                                                                                                                    "urltweet": "https://twitter.com/DevHawk/status/1503506051668140032",
                                                                                                                                                                    "inReplyToId": "1503506047327084546",
                                                                                                                                                                    "tweetUserName": "DevHawk",
                                                                                                                                                                    "subs": [
                                                                                                                                                                        {
                                                                                                                                                                            "text": "If you're a @Neo_Blockchain developer using C#, please give the new debugger preview a test drive.\n\nFeedback is always appreciated, but it's especially valuable for preview releases like this.\n\nI'm easy to find on the official Neo Discord: <a href=\"https://t.co/SYrmRzIa17\">[link]</a> (18/20)",
                                                                                                                                                                            "rawText": "If you're a @Neo_Blockchain developer using C#, please give the new debugger preview a test drive.\n\nFeedback is always appreciated, but it's especially valuable for preview releases like this.\n\nI'm easy to find on the official Neo Discord: https://t.co/SYrmRzIa17 (18/20)",
                                                                                                                                                                            "type": "tweet",
                                                                                                                                                                            "created": "Mon, 14 Mar 2022 22:59:11 GMT",
                                                                                                                                                                            "tweetId": "1503506054000173056",
                                                                                                                                                                            "urltweet": "https://twitter.com/DevHawk/status/1503506054000173056",
                                                                                                                                                                            "inReplyToId": "1503506051668140032",
                                                                                                                                                                            "tweetUserName": "DevHawk",
                                                                                                                                                                            "subs": [
                                                                                                                                                                                {
                                                                                                                                                                                    "text": "And I haven't forgotten about non-C# @Neo_Blockchain developers. Now that the preview is out, I'm reaching out to other compiler teams. I'm happy to help them update their tools to emit to the updated debugger info that drives this improved Storage Schema experience.  (19/20)",
                                                                                                                                                                                    "rawText": "And I haven't forgotten about non-C# @Neo_Blockchain developers. Now that the preview is out, I'm reaching out to other compiler teams. I'm happy to help them update their tools to emit to the updated debugger info that drives this improved Storage Schema experience.  (19/20)",
                                                                                                                                                                                    "type": "tweet",
                                                                                                                                                                                    "created": "Mon, 14 Mar 2022 22:59:12 GMT",
                                                                                                                                                                                    "tweetId": "1503506055929602049",
                                                                                                                                                                                    "urltweet": "https://twitter.com/DevHawk/status/1503506055929602049",
                                                                                                                                                                                    "inReplyToId": "1503506054000173056",
                                                                                                                                                                                    "tweetUserName": "DevHawk",
                                                                                                                                                                                    "subs": [
                                                                                                                                                                                        {
                                                                                                                                                                                            "text": "Now's a great time to get started as a @Neo_Blockchain developer. The Polaris Launchpad Hackathon just started last week. More details here: <a href=\"https://t.co/nsdj4fXH09\">[link]</a> \n\nAnyway, thanks for reading this far. Let me know what you think of the new preview. \n\n(END TRANSMISSION)",
                                                                                                                                                                                            "rawText": "Now's a great time to get started as a @Neo_Blockchain developer. The Polaris Launchpad Hackathon just started last week. More details here: https://t.co/nsdj4fXH09 \n\nAnyway, thanks for reading this far. Let me know what you think of the new preview. \n\n(END TRANSMISSION)",
                                                                                                                                                                                            "type": "tweet",
                                                                                                                                                                                            "created": "Mon, 14 Mar 2022 22:59:12 GMT",
                                                                                                                                                                                            "tweetId": "1503506057640898562",
                                                                                                                                                                                            "urltweet": "https://twitter.com/DevHawk/status/1503506057640898562",
                                                                                                                                                                                            "inReplyToId": "1503506055929602049",
                                                                                                                                                                                            "tweetUserName": "DevHawk",
                                                                                                                                                                                            "subs": [
                                                                                                                                                                                                {
                                                                                                                                                                                                    "text": "P.S. @code makes it really easy to switch back and forth between production and pre-release extensions. So even if you're worried about running preview debugger full time, it's easy enough to switch back. More details in the VSCode 1.63 release notes: <a href=\"https://t.co/hIjhPucWer\">[link]</a>",
                                                                                                                                                                                                    "rawText": "P.S. @code makes it really easy to switch back and forth between production and pre-release extensions. So even if you're worried about running preview debugger full time, it's easy enough to switch back. More details in the VSCode 1.63 release notes: https://t.co/hIjhPucWer",
                                                                                                                                                                                                    "type": "tweet",
                                                                                                                                                                                                    "created": "Mon, 14 Mar 2022 23:09:23 GMT",
                                                                                                                                                                                                    "tweetId": "1503508620083818500",
                                                                                                                                                                                                    "urltweet": "https://twitter.com/DevHawk/status/1503508620083818500",
                                                                                                                                                                                                    "inReplyToId": "1503506057640898562",
                                                                                                                                                                                                    "tweetUserName": "DevHawk"
                                                                                                                                                                                                }
                                                                                                                                                                                            ]
                                                                                                                                                                                        }
                                                                                                                                                                                    ]
                                                                                                                                                                                }
                                                                                                                                                                            ]
                                                                                                                                                                        }
                                                                                                                                                                    ]
                                                                                                                                                                }
                                                                                                                                                            ]
                                                                                                                                                        }
                                                                                                                                                    ]
                                                                                                                                                }
                                                                                                                                            ]
                                                                                                                                        }
                                                                                                                                    ]
                                                                                                                                }
                                                                                                                            ]
                                                                                                                        }
                                                                                                                    ]
                                                                                                                }
                                                                                                            ]
                                                                                                        }
                                                                                                    ]
                                                                                                }
                                                                                            ]
                                                                                        }
                                                                                    ]
                                                                                }
                                                                            ]
                                                                        }
                                                                    ]
                                                                }
                                                            ]
                                                        }
                                                    ]
                                                }
                                            ]
                                        }
                                    ]
                                }
                            ]
                        },
                        {
                            "text": "March 12",
                            "type": "calendarDay",
                            "name": "12",
                            "subs": [
                                {
                                    "text": "@patrickallmond After 3 months off? Probably not. But maybe in a couple months",
                                    "rawText": "@patrickallmond After 3 months off? Probably not. But maybe in a couple months",
                                    "type": "tweet",
                                    "created": "Sun, 13 Mar 2022 00:20:04 GMT",
                                    "tweetId": "1502801631183659008",
                                    "urltweet": "https://twitter.com/DevHawk/status/1502801631183659008",
                                    "inReplyToId": "1502776692267536391",
                                    "tweetUserName": "DevHawk"
                                },
                                {
                                    "text": "@patrickallmond Gotta catch back up to you before you decide to come out this way again. Cant have you show me up in my home gym. 😅",
                                    "rawText": "@patrickallmond Gotta catch back up to you before you decide to come out this way again. Cant have you show me up in my home gym. 😅",
                                    "type": "tweet",
                                    "created": "Sat, 12 Mar 2022 17:50:17 GMT",
                                    "tweetId": "1502703542049538049",
                                    "urltweet": "https://twitter.com/DevHawk/status/1502703542049538049",
                                    "inReplyToId": "1502701676419026954",
                                    "tweetUserName": "DevHawk"
                                },
                                {
                                    "text": "@GrabowskiDylan Yeah, took me out for most of Feb. Got over the worst of it in a few days, but then was easily exhausted for weeks",
                                    "rawText": "@GrabowskiDylan Yeah, took me out for most of Feb. Got over the worst of it in a few days, but then was easily exhausted for weeks",
                                    "type": "tweet",
                                    "created": "Sat, 12 Mar 2022 17:49:07 GMT",
                                    "tweetId": "1502703248557285378",
                                    "urltweet": "https://twitter.com/DevHawk/status/1502703248557285378",
                                    "inReplyToId": "1502701949518450689",
                                    "tweetUserName": "DevHawk"
                                },
                                {
                                    "text": "Finally got back to the gym this week after nearly 3 months. Holidays, omicron wave, getting covid anyway despite precautions and trip east have kept me away too long. I'm sore, but that will pass soon enough. <a href=\"https://t.co/s0UFFh44cc\">[link]</a>",
                                    "rawText": "Finally got back to the gym this week after nearly 3 months. Holidays, omicron wave, getting covid anyway despite precautions and trip east have kept me away too long. I'm sore, but that will pass soon enough. https://t.co/s0UFFh44cc",
                                    "type": "tweet",
                                    "created": "Sat, 12 Mar 2022 17:32:13 GMT",
                                    "tweetId": "1502698992316010496",
                                    "urltweet": "https://twitter.com/DevHawk/status/1502698992316010496",
                                    "tweetUserName": "DevHawk"
                                }
                            ]
                        },
                        {
                            "text": "March 7",
                            "type": "calendarDay",
                            "name": "07",
                            "subs": [
                                {
                                    "text": "Like last time, I'll be spending a lot of my time during the Neo Polaris Launchpad Hackathon (<a href=\"https://t.co/nsdj4fXH09\">[link]</a>) helping participants and answering questions about @Neo_Blockchain development and the Neo Blockchain Toolkit. https://t.co/wvGWX7OclY",
                                    "rawText": "Like last time, I'll be spending a lot of my time during the Neo Polaris Launchpad Hackathon (https://t.co/nsdj4fXH09) helping participants and answering questions about @Neo_Blockchain development and the Neo Blockchain Toolkit. https://t.co/wvGWX7OclY",
                                    "type": "tweet",
                                    "created": "Mon, 07 Mar 2022 15:28:08 GMT",
                                    "tweetId": "1500855828085043208",
                                    "urltweet": "https://twitter.com/DevHawk/status/1500855828085043208",
                                    "tweetUserName": "DevHawk",
                                    "subs": [
                                        {
                                            "text": "I love events like this. The direct line to the folks using the tools under the pressure of competition is invaluable. Feedback we got last time led directly to product improvements that benefit the entire community.",
                                            "rawText": "I love events like this. The direct line to the folks using the tools under the pressure of competition is invaluable. Feedback we got last time led directly to product improvements that benefit the entire community.",
                                            "type": "tweet",
                                            "created": "Mon, 07 Mar 2022 15:28:09 GMT",
                                            "tweetId": "1500855830354096134",
                                            "urltweet": "https://twitter.com/DevHawk/status/1500855830354096134",
                                            "inReplyToId": "1500855828085043208",
                                            "tweetUserName": "DevHawk",
                                            "subs": [
                                                {
                                                    "text": "There are significant debugger improvements that will be available (in preview) this week. Neo C# tooling updates to support these debugger improvements will be available later this month - just in time for the start of the hackathon in April!\n \n<a href=\"https://t.co/ZOyqOQYiyJ\">[link]</a>",
                                                    "rawText": "There are significant debugger improvements that will be available (in preview) this week. Neo C# tooling updates to support these debugger improvements will be available later this month - just in time for the start of the hackathon in April!\n \nhttps://t.co/ZOyqOQYiyJ",
                                                    "type": "tweet",
                                                    "created": "Mon, 07 Mar 2022 15:28:09 GMT",
                                                    "tweetId": "1500855832375824384",
                                                    "urltweet": "https://twitter.com/DevHawk/status/1500855832375824384",
                                                    "inReplyToId": "1500855830354096134",
                                                    "tweetUserName": "DevHawk",
                                                    "subs": [
                                                        {
                                                            "text": "If you're participating in Neo Polaris Launchpad, please don't hesitate to reach out to me with questions.\n\nThe best way to reach me is via the official @Neo_Blockchain Discord (<a href=\"https://t.co/wkxYs9CCV9\">[link]</a>), though you can obviously also reach me here on Twitter as well.\n\nGood Luck!",
                                                            "rawText": "If you're participating in Neo Polaris Launchpad, please don't hesitate to reach out to me with questions.\n\nThe best way to reach me is via the official @Neo_Blockchain Discord (https://t.co/wkxYs9CCV9), though you can obviously also reach me here on Twitter as well.\n\nGood Luck!",
                                                            "type": "tweet",
                                                            "created": "Mon, 07 Mar 2022 15:28:10 GMT",
                                                            "tweetId": "1500855834401591299",
                                                            "urltweet": "https://twitter.com/DevHawk/status/1500855834401591299",
                                                            "inReplyToId": "1500855832375824384",
                                                            "tweetUserName": "DevHawk"
                                                        }
                                                    ]
                                                }
                                            ]
                                        }
                                    ]
                                }
                            ]
                        },
                        {
                            "text": "March 6",
                            "type": "calendarDay",
                            "name": "06",
                            "subs": [
                                {
                                    "text": "My son didn't know the term \"disc jockey\" 🤣🤣🤣 #ImOld",
                                    "rawText": "My son didn't know the term \"disc jockey\" 🤣🤣🤣 #ImOld",
                                    "type": "tweet",
                                    "created": "Sun, 06 Mar 2022 20:01:08 GMT",
                                    "tweetId": "1500562141853663239",
                                    "urltweet": "https://twitter.com/DevHawk/status/1500562141853663239",
                                    "tweetUserName": "DevHawk"
                                }
                            ]
                        },
                        {
                            "text": "March 5",
                            "type": "calendarDay",
                            "name": "05",
                            "subs": [
                                {
                                    "text": "Would have liked to see a @SeattleKraken win, but the @Capitals need the standings points more.\n\nMy eldest said tonight was like the opposite of watching say a Penguins /Flyers game. Those games, we're usually rooting for a meteor to hit the arena.",
                                    "rawText": "Would have liked to see a @SeattleKraken win, but the @Capitals need the standings points more.\n\nMy eldest said tonight was like the opposite of watching say a Penguins /Flyers game. Those games, we're usually rooting for a meteor to hit the arena.",
                                    "type": "tweet",
                                    "created": "Sun, 06 Mar 2022 02:35:56 GMT",
                                    "tweetId": "1500299108178923522",
                                    "urltweet": "https://twitter.com/DevHawk/status/1500299108178923522",
                                    "tweetUserName": "DevHawk"
                                },
                                {
                                    "text": "Love to see @Capitals saluting @SeattleKraken captain Mark Giordano in his 1000th game",
                                    "rawText": "Love to see @Capitals saluting @SeattleKraken captain Mark Giordano in his 1000th game",
                                    "type": "tweet",
                                    "created": "Sun, 06 Mar 2022 00:28:25 GMT",
                                    "tweetId": "1500267016783073282",
                                    "urltweet": "https://twitter.com/DevHawk/status/1500267016783073282",
                                    "tweetUserName": "DevHawk"
                                },
                                {
                                    "text": "My wife and parents conspired to bring me back east to catch @SeattleKraken v. @Capitals.\n\nI've been a Caps fan since I was a kid. And of course I support the Kraken - my home team. So its awesome to get the chance to see these two teams face off. <a href=\"https://t.co/foLDc9WuM9\">[link]</a>",
                                    "rawText": "My wife and parents conspired to bring me back east to catch @SeattleKraken v. @Capitals.\n\nI've been a Caps fan since I was a kid. And of course I support the Kraken - my home team. So its awesome to get the chance to see these two teams face off. https://t.co/foLDc9WuM9",
                                    "type": "tweet",
                                    "created": "Sat, 05 Mar 2022 23:33:47 GMT",
                                    "tweetId": "1500253269993660417",
                                    "urltweet": "https://twitter.com/DevHawk/status/1500253269993660417",
                                    "tweetUserName": "DevHawk",
                                    "subs": [
                                        {
                                            "text": "I figured there would be of plenty of folks in Caps jerseys, so I wore my Kraken jersey. Way out numbered, but I've seen more Seattle jerseys than I was expecting",
                                            "rawText": "I figured there would be of plenty of folks in Caps jerseys, so I wore my Kraken jersey. Way out numbered, but I've seen more Seattle jerseys than I was expecting",
                                            "type": "tweet",
                                            "created": "Sat, 05 Mar 2022 23:36:20 GMT",
                                            "tweetId": "1500253912321904648",
                                            "urltweet": "https://twitter.com/DevHawk/status/1500253912321904648",
                                            "inReplyToId": "1500253269993660417",
                                            "tweetUserName": "DevHawk"
                                        }
                                    ]
                                }
                            ]
                        },
                        {
                            "text": "March 4",
                            "type": "calendarDay",
                            "name": "04",
                            "subs": [
                                {
                                    "text": "@ZackCz Can we have Al Franken back in office?",
                                    "rawText": "@ZackCz Can we have Al Franken back in office?",
                                    "type": "tweet",
                                    "created": "Fri, 04 Mar 2022 22:38:14 GMT",
                                    "tweetId": "1499876901187379206",
                                    "urltweet": "https://twitter.com/DevHawk/status/1499876901187379206",
                                    "inReplyToId": "1499876150767718400",
                                    "tweetUserName": "DevHawk"
                                },
                                {
                                    "text": "@roschler I'm on vacation, I'm not hiding under a rock without access to the internet",
                                    "rawText": "@roschler I'm on vacation, I'm not hiding under a rock without access to the internet",
                                    "type": "tweet",
                                    "created": "Fri, 04 Mar 2022 20:48:51 GMT",
                                    "tweetId": "1499849375404675080",
                                    "urltweet": "https://twitter.com/DevHawk/status/1499849375404675080",
                                    "inReplyToId": "1499846723270852609",
                                    "tweetUserName": "DevHawk"
                                },
                                {
                                    "text": "Hey, I think I know that guy <a href=\"https://t.co/X1VvJTee6g\">[link]</a>",
                                    "rawText": "Hey, I think I know that guy https://t.co/X1VvJTee6g",
                                    "type": "tweet",
                                    "created": "Fri, 04 Mar 2022 18:20:23 GMT",
                                    "tweetId": "1499812013752659972",
                                    "urltweet": "https://twitter.com/DevHawk/status/1499812013752659972",
                                    "tweetUserName": "DevHawk"
                                }
                            ]
                        },
                        {
                            "text": "March 2",
                            "type": "calendarDay",
                            "name": "02",
                            "subs": [
                                {
                                    "text": "Good luck in your future endeavors @migueldeicaza <a href=\"https://t.co/8ePWxS8XTq\">[link]</a>",
                                    "rawText": "Good luck in your future endeavors @migueldeicaza https://t.co/8ePWxS8XTq",
                                    "type": "tweet",
                                    "created": "Thu, 03 Mar 2022 04:22:57 GMT",
                                    "tweetId": "1499238878930079746",
                                    "urltweet": "https://twitter.com/DevHawk/status/1499238878930079746",
                                    "tweetUserName": "DevHawk"
                                }
                            ]
                        },
                        {
                            "text": "March 1",
                            "type": "calendarDay",
                            "name": "01",
                            "subs": [
                                {
                                    "text": "@clairernovotny Not really, though the primitives are there obviously.\n\nI'm looking for stuff like path comparison (case insensitive on windows vs case sensitive elsewhere) &amp; processing paths that may come from another platform (processing a unix path via Path.Combine on Windows or vis-versa)",
                                    "rawText": "@clairernovotny Not really, though the primitives are there obviously.\n\nI'm looking for stuff like path comparison (case insensitive on windows vs case sensitive elsewhere) &amp; processing paths that may come from another platform (processing a unix path via Path.Combine on Windows or vis-versa)",
                                    "type": "tweet",
                                    "created": "Tue, 01 Mar 2022 21:13:10 GMT",
                                    "tweetId": "1498768329053380609",
                                    "urltweet": "https://twitter.com/DevHawk/status/1498768329053380609",
                                    "inReplyToId": "1498766728666533891",
                                    "tweetUserName": "DevHawk",
                                    "subs": [
                                        {
                                            "text": "@clairernovotny \"What is this 'Base Class Library' you speak of @clairernovotny?\" asked a guy who used to work on the Midori fork of the Base Class Library 🤣",
                                            "rawText": "@clairernovotny \"What is this 'Base Class Library' you speak of @clairernovotny?\" asked a guy who used to work on the Midori fork of the Base Class Library 🤣",
                                            "type": "tweet",
                                            "created": "Tue, 01 Mar 2022 21:15:58 GMT",
                                            "tweetId": "1498769033776152576",
                                            "urltweet": "https://twitter.com/DevHawk/status/1498769033776152576",
                                            "inReplyToId": "1498768329053380609",
                                            "tweetUserName": "DevHawk",
                                            "subs": [
                                                {
                                                    "text": "@clairernovotny I was hoping to find something like <a href=\"https://t.co/zNjFX5OymW\">[link]</a> but as a stand alone package",
                                                    "rawText": "@clairernovotny I was hoping to find something like https://t.co/zNjFX5OymW but as a stand alone package",
                                                    "type": "tweet",
                                                    "created": "Tue, 08 Mar 2022 18:50:45 GMT",
                                                    "tweetId": "1501269205823344647",
                                                    "urltweet": "https://twitter.com/DevHawk/status/1501269205823344647",
                                                    "inReplyToId": "1498769033776152576",
                                                    "tweetUserName": "DevHawk"
                                                }
                                            ]
                                        }
                                    ]
                                },
                                {
                                    "text": "Is there a xplat .NET library for working with file system paths that I'm not aware of?\n\nI could roll my own, but I'd rather use an existing (i.e. tested) library. I've done enough file system work to know there be dragons in the edge cases.",
                                    "rawText": "Is there a xplat .NET library for working with file system paths that I'm not aware of?\n\nI could roll my own, but I'd rather use an existing (i.e. tested) library. I've done enough file system work to know there be dragons in the edge cases.",
                                    "type": "tweet",
                                    "created": "Tue, 01 Mar 2022 21:05:54 GMT",
                                    "tweetId": "1498766501339287556",
                                    "urltweet": "https://twitter.com/DevHawk/status/1498766501339287556",
                                    "tweetUserName": "DevHawk"
                                }
                            ]
                        }
                    ]
                }
            ]
        }
    }
}