{
    "opml": {
        "head": {
            "title": "cluelessnewbie tweets",
            "dateCreated": "Sat, 01 Jan 2022 14:23:47 GMT",
            "expansionState": "1,2",
            "urlPublic": "http://tweets.opml.org/cluelessnewbie/tweets.opml",
            "urlUpdateSocket": "ws://tweets.opml.org:1481/",
            "dateModified": "Sun, 13 Feb 2022 23:18:29 GMT"
        },
        "body": {
            "subs": [
                {
                    "text": "February 2022",
                    "type": "calendarMonth",
                    "name": "february2022",
                    "subs": [
                        {
                            "text": "February 13",
                            "type": "calendarDay",
                            "name": "13",
                            "subs": [
                                {
                                    "text": "I am going to tweet again baby.",
                                    "type": "tweet",
                                    "created": "Sun, 13 Feb 2022 23:17:59 GMT",
                                    "tweetId": "1493001536674349057",
                                    "urltweet": "https://twitter.com/cluelessnewbie/status/1493001536674349057",
                                    "tweetUserName": "cluelessnewbie"
                                },
                                {
                                    "text": "### Another verse from Waterloo Sunset\n\nBut I don't need no friends\n\nAs long as I gaze on\n\nWaterloo sunset\n\nI am in paradise",
                                    "type": "tweet",
                                    "created": "Sun, 13 Feb 2022 19:45:46 GMT",
                                    "tweetId": "1492948131796983812",
                                    "urltweet": "https://twitter.com/cluelessnewbie/status/1492948131796983812",
                                    "tweetUserName": "cluelessnewbie"
                                },
                                {
                                    "text": "### Waterloo sunset\n\nDirty old river, must you keep rolling\n\nFlowing into the night?\n\nPeople so busy, make me feel dizzy\n\nTaxi light shines so bright",
                                    "type": "tweet",
                                    "created": "Sun, 13 Feb 2022 19:42:29 GMT",
                                    "tweetId": "1492947303828803587",
                                    "urltweet": "https://twitter.com/cluelessnewbie/status/1492947303828803587",
                                    "tweetUserName": "cluelessnewbie"
                                },
                                {
                                    "text": "### Have a cuppa tea\n\nGranny's always ravin' and rantin',\n\nAnd she's always puffin' and pantin',\n\nAnd she's always screaming and shouting,\n\nAnd she's always brewing up tea.",
                                    "type": "tweet",
                                    "created": "Sun, 13 Feb 2022 16:43:21 GMT",
                                    "tweetId": "1492902222753148933",
                                    "urltweet": "https://twitter.com/cluelessnewbie/status/1492902222753148933",
                                    "tweetUserName": "cluelessnewbie"
                                },
                                {
                                    "text": "### Another test tweet\n\nOne.\n\nTwo.\n\nThree.",
                                    "type": "tweet",
                                    "created": "Sun, 13 Feb 2022 15:50:23 GMT",
                                    "tweetId": "1492888893112426496",
                                    "urltweet": "https://twitter.com/cluelessnewbie/status/1492888893112426496",
                                    "tweetUserName": "cluelessnewbie"
                                },
                                {
                                    "text": "### A multi-line tweet\n\nI am going to have this appear as a titled item in my RSS feed. This is a test post I will use.\n\nThis is another paragraph. \n\nAnd another.",
                                    "type": "tweet",
                                    "created": "Sun, 13 Feb 2022 15:48:24 GMT",
                                    "tweetId": "1492888394103406598",
                                    "urltweet": "https://twitter.com/cluelessnewbie/status/1492888394103406598",
                                    "tweetUserName": "cluelessnewbie"
                                }
                            ]
                        },
                        {
                            "text": "February 12",
                            "type": "calendarDay",
                            "name": "12",
                            "subs": [
                                {
                                    "text": "We need another test tweet to prime the pump.",
                                    "type": "tweet",
                                    "created": "Sat, 12 Feb 2022 18:16:28 GMT",
                                    "tweetId": "1492563269533450246",
                                    "urltweet": "https://twitter.com/cluelessnewbie/status/1492563269533450246",
                                    "tweetUserName": "cluelessnewbie"
                                },
                                {
                                    "text": "Apple changes employees’ titles to ‘associate’ after they leave more testing",
                                    "type": "tweet",
                                    "created": "Sat, 12 Feb 2022 16:56:52 GMT",
                                    "tweetId": "1492543238896590849",
                                    "urltweet": "https://twitter.com/cluelessnewbie/status/1492543238896590849",
                                    "tweetUserName": "cluelessnewbie"
                                },
                                {
                                    "text": "Apple changes employees’ titles to ‘associate’ after they leave.\n\nanother test",
                                    "type": "tweet",
                                    "created": "Sat, 12 Feb 2022 15:57:54 GMT",
                                    "tweetId": "1492528397528051716",
                                    "urltweet": "https://twitter.com/cluelessnewbie/status/1492528397528051716",
                                    "tweetUserName": "cluelessnewbie"
                                }
                            ]
                        }
                    ]
                }
            ]
        }
    }
}