{
    "opml": {
        "head": {
            "title": "ReaderRJ tweets",
            "dateCreated": "Mon, 24 Jan 2022 15:37:34 GMT",
            "expansionState": "1,2",
            "urlPublic": "http://tweets.opml.org/ReaderRJ/tweets.opml",
            "urlUpdateSocket": "ws://tweets.opml.org:1481/",
            "dateModified": "Tue, 26 Apr 2022 14:12:09 GMT"
        },
        "body": {
            "subs": [
                {
                    "text": "April 2022",
                    "type": "calendarMonth",
                    "name": "april2022",
                    "subs": [
                        {
                            "text": "April 26",
                            "type": "calendarDay",
                            "name": "26",
                            "subs": [
                                {
                                    "text": "The far right are celebrating the @elonmusk Twitter takeover. They hope they’ll be able to get back on the platform to spread their hate and lies. \n\nSign the @HOPEnothate open letter calling on Musk to keep hate off @Twitter now 👇 <a href=\"https://t.co/LM2LvxLMdd\">[link]</a>",
                                    "rawText": "The far right are celebrating the @elonmusk Twitter takeover. They hope they’ll be able to get back on the platform to spread their hate and lies. \n\nSign the @HOPEnothate open letter calling on Musk to keep hate off @Twitter now 👇 https://t.co/LM2LvxLMdd",
                                    "type": "tweet",
                                    "created": "Tue, 26 Apr 2022 14:04:51 GMT",
                                    "tweetId": "1518954261446545409",
                                    "urltweet": "https://twitter.com/ReaderRJ/status/1518954261446545409",
                                    "tweetUserName": "ReaderRJ"
                                }
                            ]
                        },
                        {
                            "text": "April 17",
                            "type": "calendarDay",
                            "name": "17",
                            "subs": [
                                {
                                    "text": "In #Ukraine and the world over, people are losing everything they have because of violent conflict. Urge Home Secretary Priti Patel to take compassionate action for the world’s refugees, and rethink the harmful Nationality and Borders Bill <a href=\"https://t.co/EK2bJIIvEv\">[link]</a>",
                                    "rawText": "In #Ukraine and the world over, people are losing everything they have because of violent conflict. Urge Home Secretary Priti Patel to take compassionate action for the world’s refugees, and rethink the harmful Nationality and Borders Bill https://t.co/EK2bJIIvEv",
                                    "type": "tweet",
                                    "created": "Sun, 17 Apr 2022 10:05:25 GMT",
                                    "tweetId": "1515632515062583298",
                                    "urltweet": "https://twitter.com/ReaderRJ/status/1515632515062583298",
                                    "tweetUserName": "ReaderRJ"
                                }
                            ]
                        },
                        {
                            "text": "April 14",
                            "type": "calendarDay",
                            "name": "14",
                            "subs": [
                                {
                                    "text": ".@BorisJohnson and @rishisunak broke the law. They have to resign. #Partygate - Sign the Petition! <a href=\"https://t.co/tB84yZf5sA\">[link]</a> via @UKChange",
                                    "rawText": ".@BorisJohnson and @rishisunak broke the law. They have to resign. #Partygate - Sign the Petition! https://t.co/tB84yZf5sA via @UKChange",
                                    "type": "tweet",
                                    "created": "Thu, 14 Apr 2022 19:17:23 GMT",
                                    "tweetId": "1514684261042999300",
                                    "urltweet": "https://twitter.com/ReaderRJ/status/1514684261042999300",
                                    "tweetUserName": "ReaderRJ"
                                },
                                {
                                    "text": "It's Not About The Pasta, Kevin. | Jack Monroe <a href=\"https://t.co/e40xLjjLdh\">[link]</a> via @BootstrapCook",
                                    "rawText": "It's Not About The Pasta, Kevin. | Jack Monroe https://t.co/e40xLjjLdh via @BootstrapCook",
                                    "type": "tweet",
                                    "created": "Thu, 14 Apr 2022 17:22:26 GMT",
                                    "tweetId": "1514655330172641284",
                                    "urltweet": "https://twitter.com/ReaderRJ/status/1514655330172641284",
                                    "tweetUserName": "ReaderRJ"
                                }
                            ]
                        },
                        {
                            "text": "April 11",
                            "type": "calendarDay",
                            "name": "11",
                            "subs": [
                                {
                                    "text": "Why are criminal barristers taking part in an \"unnecessary and irresponsible strike\"? <a href=\"https://t.co/C01xnPFcXH\">[link]</a>",
                                    "rawText": "Why are criminal barristers taking part in an \"unnecessary and irresponsible strike\"? https://t.co/C01xnPFcXH",
                                    "type": "tweet",
                                    "created": "Mon, 11 Apr 2022 12:13:05 GMT",
                                    "tweetId": "1513490318729134084",
                                    "urltweet": "https://twitter.com/ReaderRJ/status/1513490318729134084",
                                    "tweetUserName": "ReaderRJ"
                                }
                            ]
                        },
                        {
                            "text": "April 6",
                            "type": "calendarDay",
                            "name": "06",
                            "subs": [
                                {
                                    "text": "Selling off Channel 4, a profit-making publicly-owned asset, makes no sense. This puts jobs, small businesses and popular TV shows like #GreatBritishBakeOff and #Gogglebox at risk. @NadineDorries get your hands off @Channel4 #HandsOffChannel4 @We_ownit <a href=\"https://t.co/uJUBD03HKO\">[link]</a>",
                                    "rawText": "Selling off Channel 4, a profit-making publicly-owned asset, makes no sense. This puts jobs, small businesses and popular TV shows like #GreatBritishBakeOff and #Gogglebox at risk. @NadineDorries get your hands off @Channel4 #HandsOffChannel4 @We_ownit https://t.co/uJUBD03HKO",
                                    "type": "tweet",
                                    "created": "Wed, 06 Apr 2022 12:15:41 GMT",
                                    "tweetId": "1511679032156426241",
                                    "urltweet": "https://twitter.com/ReaderRJ/status/1511679032156426241",
                                    "tweetUserName": "ReaderRJ"
                                }
                            ]
                        },
                        {
                            "text": "April 5",
                            "type": "calendarDay",
                            "name": "05",
                            "subs": [
                                {
                                    "text": "Stop the privatisation of Channel 4 @NadineDorries <a href=\"https://t.co/vrfFs9JJsJ\">[link]</a> via @UKChange",
                                    "rawText": "Stop the privatisation of Channel 4 @NadineDorries https://t.co/vrfFs9JJsJ via @UKChange",
                                    "type": "tweet",
                                    "created": "Tue, 05 Apr 2022 21:25:38 GMT",
                                    "tweetId": "1511455045228937228",
                                    "urltweet": "https://twitter.com/ReaderRJ/status/1511455045228937228",
                                    "tweetUserName": "ReaderRJ"
                                },
                                {
                                    "text": "Stop the privatisation of Channel 4 @NadineDorries - Sign the Petition! <a href=\"https://t.co/lJJakr6tCk\">[link]</a> via @UKChange",
                                    "rawText": "Stop the privatisation of Channel 4 @NadineDorries - Sign the Petition! https://t.co/lJJakr6tCk via @UKChange",
                                    "type": "tweet",
                                    "created": "Tue, 05 Apr 2022 18:50:31 GMT",
                                    "tweetId": "1511416008711577605",
                                    "urltweet": "https://twitter.com/ReaderRJ/status/1511416008711577605",
                                    "tweetUserName": "ReaderRJ"
                                }
                            ]
                        }
                    ]
                }
            ]
        }
    }
}