{
    "opml": {
        "head": {
            "title": "mathling tweets",
            "dateCreated": "Sun, 12 Jun 2022 16:14:12 GMT",
            "expansionState": "1,2",
            "urlPublic": "http://tweets.opml.org/mathling/tweets.opml",
            "urlUpdateSocket": "ws://tweets.opml.org:1481/",
            "dateModified": "Mon, 01 Aug 2022 14:18:06 GMT"
        },
        "body": {
            "subs": [
                {
                    "text": "August 2022",
                    "type": "calendarMonth",
                    "name": "august2022",
                    "subs": [
                        {
                            "text": "August 1",
                            "type": "calendarDay",
                            "name": "01",
                            "subs": [
                                {
                                    "text": "It begins!\n\nTommie Usdin \"Destructive Consistency\" #balisage2022",
                                    "rawText": "It begins!\n\nTommie Usdin \"Destructive Consistency\" #balisage2022",
                                    "type": "tweet",
                                    "created": "Mon, 01 Aug 2022 14:04:32 GMT",
                                    "tweetId": "1554105805355380736",
                                    "urltweet": "https://twitter.com/mathling/status/1554105805355380736",
                                    "tweetUserName": "mathling",
                                    "subs": [
                                        {
                                            "text": "\"Balisage is not television\" #balisage2022",
                                            "rawText": "\"Balisage is not television\" #balisage2022",
                                            "type": "tweet",
                                            "created": "Mon, 01 Aug 2022 14:08:39 GMT",
                                            "tweetId": "1554106842577416192",
                                            "urltweet": "https://twitter.com/mathling/status/1554106842577416192",
                                            "inReplyToId": "1554105805355380736",
                                            "tweetUserName": "mathling"
                                        }
                                    ]
                                },
                                {
                                    "text": "Minutes away from the start of  #balisage2022 !",
                                    "rawText": "Minutes away from the start of  #balisage2022 !",
                                    "type": "tweet",
                                    "created": "Mon, 01 Aug 2022 13:58:51 GMT",
                                    "tweetId": "1554104374388854784",
                                    "urltweet": "https://twitter.com/mathling/status/1554104374388854784",
                                    "tweetUserName": "mathling"
                                }
                            ]
                        }
                    ]
                }
            ]
        }
    }
}