{
    "opml": {
        "head": {
            "title": "chiguire tweets",
            "dateCreated": "Thu, 10 Feb 2022 23:35:37 GMT",
            "expansionState": "1,2",
            "urlPublic": "http://tweets.opml.org/chiguire/tweets.opml",
            "urlUpdateSocket": "ws://tweets.opml.org:1481/",
            "dateModified": "Thu, 01 Sep 2022 10:02:18 GMT"
        },
        "body": {
            "subs": [
                {
                    "text": "September 2022",
                    "type": "calendarMonth",
                    "name": "september2022",
                    "subs": [
                        {
                            "text": "September 1",
                            "type": "calendarDay",
                            "name": "01",
                            "subs": [
                                {
                                    "text": "@lsjoq_ Suerte y gaceta hípica 🐎",
                                    "rawText": "@lsjoq_ Suerte y gaceta hípica 🐎",
                                    "type": "tweet",
                                    "created": "Thu, 01 Sep 2022 10:00:48 GMT",
                                    "tweetId": "1565278491792351232",
                                    "urltweet": "https://twitter.com/chiguire/status/1565278491792351232",
                                    "inReplyToId": "1565274173785661447",
                                    "tweetUserName": "chiguire"
                                },
                                {
                                    "text": "@LucenaPerezM <a href=\"https://t.co/SuF6UBvllp\">[link]</a>",
                                    "rawText": "@LucenaPerezM https://t.co/SuF6UBvllp",
                                    "type": "tweet",
                                    "created": "Thu, 01 Sep 2022 07:58:15 GMT",
                                    "tweetId": "1565247651972538368",
                                    "urltweet": "https://twitter.com/chiguire/status/1565247651972538368",
                                    "inReplyToId": "1565241740851912705",
                                    "tweetUserName": "chiguire"
                                }
                            ]
                        }
                    ]
                }
            ]
        }
    }
}