{
    "opml": {
        "head": {
            "title": "sillygwailo tweets",
            "dateCreated": "Sun, 23 Jan 2022 23:52:54 GMT",
            "expansionState": "1,2",
            "urlPublic": "http://tweets.opml.org/sillygwailo/tweets.opml",
            "urlUpdateSocket": "ws://tweets.opml.org:1481/",
            "dateModified": "Sun, 04 Sep 2022 18:40:11 GMT"
        },
        "body": {
            "subs": [
                {
                    "text": "September 2022",
                    "type": "calendarMonth",
                    "name": "september2022",
                    "subs": [
                        {
                            "text": "September 4",
                            "type": "calendarDay",
                            "name": "04",
                            "subs": [
                                {
                                    "text": "Have you ever heard of a Starbucks closing permanently but then re-opening at the same location? That’s what happened at the 370 King St. W. location under the Hyatt Regency in Toronto. <a href=\"https://t.co/95jXOUzkTx\">[link]</a>",
                                    "rawText": "Have you ever heard of a Starbucks closing permanently but then re-opening at the same location? That’s what happened at the 370 King St. W. location under the Hyatt Regency in Toronto. https://t.co/95jXOUzkTx",
                                    "type": "tweet",
                                    "created": "Sun, 04 Sep 2022 18:31:07 GMT",
                                    "tweetId": "1566494081542406146",
                                    "urltweet": "https://twitter.com/sillygwailo/status/1566494081542406146",
                                    "tweetUserName": "sillygwailo"
                                }
                            ]
                        },
                        {
                            "text": "September 3",
                            "type": "calendarDay",
                            "name": "03",
                            "subs": [
                                {
                                    "text": "Extroverts in Toronto seem happy tonight.",
                                    "rawText": "Extroverts in Toronto seem happy tonight.",
                                    "type": "tweet",
                                    "created": "Sun, 04 Sep 2022 02:41:35 GMT",
                                    "tweetId": "1566255123080384514",
                                    "urltweet": "https://twitter.com/sillygwailo/status/1566255123080384514",
                                    "tweetUserName": "sillygwailo"
                                },
                                {
                                    "text": "@rtanglao I haven’t done e-assist yet. I want to test it out first, i.e. not have somewhere I have to be, before choosing it at a bike share stall.",
                                    "rawText": "@rtanglao I haven’t done e-assist yet. I want to test it out first, i.e. not have somewhere I have to be, before choosing it at a bike share stall.",
                                    "type": "tweet",
                                    "created": "Sun, 04 Sep 2022 02:11:01 GMT",
                                    "tweetId": "1566247429325955073",
                                    "urltweet": "https://twitter.com/sillygwailo/status/1566247429325955073",
                                    "inReplyToId": "1566245663763230720",
                                    "tweetUserName": "sillygwailo"
                                },
                                {
                                    "text": "@rtanglao Coffee and donuts (I prefer the American spelling) at Lucky’s Doughnuts on Main and E. 13th. That’s still my favourite coffee shop of all time.",
                                    "rawText": "@rtanglao Coffee and donuts (I prefer the American spelling) at Lucky’s Doughnuts on Main and E. 13th. That’s still my favourite coffee shop of all time.",
                                    "type": "tweet",
                                    "created": "Sun, 04 Sep 2022 02:09:25 GMT",
                                    "tweetId": "1566247026068684801",
                                    "urltweet": "https://twitter.com/sillygwailo/status/1566247026068684801",
                                    "inReplyToId": "1566245489812860928",
                                    "tweetUserName": "sillygwailo"
                                },
                                {
                                    "text": "@ksituan I am buying the heck out of this map.",
                                    "rawText": "@ksituan I am buying the heck out of this map.",
                                    "type": "tweet",
                                    "created": "Sun, 04 Sep 2022 01:44:12 GMT",
                                    "tweetId": "1566240681856835586",
                                    "urltweet": "https://twitter.com/sillygwailo/status/1566240681856835586",
                                    "inReplyToId": "1565115750624403456",
                                    "tweetUserName": "sillygwailo"
                                },
                                {
                                    "text": "@CimberFan This is good, because Adam Cimber is good, and it means dancing to his walk-up song more often. <a href=\"https://t.co/zFhrtXNQMw\">[link]</a>",
                                    "rawText": "@CimberFan This is good, because Adam Cimber is good, and it means dancing to his walk-up song more often. https://t.co/zFhrtXNQMw",
                                    "type": "tweet",
                                    "created": "Sun, 04 Sep 2022 01:26:41 GMT",
                                    "tweetId": "1566236272871473155",
                                    "urltweet": "https://twitter.com/sillygwailo/status/1566236272871473155",
                                    "inReplyToId": "1565894849391386624",
                                    "tweetUserName": "sillygwailo"
                                },
                                {
                                    "text": "@rtanglao I’ll make both, obvs.!",
                                    "rawText": "@rtanglao I’ll make both, obvs.!",
                                    "type": "tweet",
                                    "created": "Sun, 04 Sep 2022 00:50:54 GMT",
                                    "tweetId": "1566227266224488448",
                                    "urltweet": "https://twitter.com/sillygwailo/status/1566227266224488448",
                                    "inReplyToId": "1566226696348794880",
                                    "tweetUserName": "sillygwailo"
                                },
                                {
                                    "text": "@rtanglao C Chaan!  I just made it again recently. Yum yum! <a href=\"https://t.co/PClWEaU4ck\">[link]</a>",
                                    "rawText": "@rtanglao C Chaan!  I just made it again recently. Yum yum! https://t.co/PClWEaU4ck",
                                    "type": "tweet",
                                    "created": "Sun, 04 Sep 2022 00:38:02 GMT",
                                    "tweetId": "1566224029324902407",
                                    "urltweet": "https://twitter.com/sillygwailo/status/1566224029324902407",
                                    "inReplyToId": "1566222993533321216",
                                    "tweetUserName": "sillygwailo"
                                },
                                {
                                    "text": "@rtanglao I don’t remember ever having mapo tofu, so XLB.",
                                    "rawText": "@rtanglao I don’t remember ever having mapo tofu, so XLB.",
                                    "type": "tweet",
                                    "created": "Sun, 04 Sep 2022 00:29:29 GMT",
                                    "tweetId": "1566221879580495872",
                                    "urltweet": "https://twitter.com/sillygwailo/status/1566221879580495872",
                                    "inReplyToId": "1566221530555883520",
                                    "tweetUserName": "sillygwailo"
                                },
                                {
                                    "text": "@rtanglao Mach dir keine Sorgen. Lederjackenwetter kommt.",
                                    "rawText": "@rtanglao Mach dir keine Sorgen. Lederjackenwetter kommt.",
                                    "type": "tweet",
                                    "created": "Sun, 04 Sep 2022 00:04:47 GMT",
                                    "tweetId": "1566215663118606337",
                                    "urltweet": "https://twitter.com/sillygwailo/status/1566215663118606337",
                                    "inReplyToId": "1566215263699484673",
                                    "tweetUserName": "sillygwailo"
                                },
                                {
                                    "text": "@rtanglao Canada’s national sport. In other words, baseball.",
                                    "rawText": "@rtanglao Canada’s national sport. In other words, baseball.",
                                    "type": "tweet",
                                    "created": "Sun, 04 Sep 2022 00:03:23 GMT",
                                    "tweetId": "1566215311782707204",
                                    "urltweet": "https://twitter.com/sillygwailo/status/1566215311782707204",
                                    "inReplyToId": "1566214900883816449",
                                    "tweetUserName": "sillygwailo"
                                },
                                {
                                    "text": "@rtanglao <a href=\"https://t.co/NfPLlRHAUg\">[link]</a>",
                                    "rawText": "@rtanglao https://t.co/NfPLlRHAUg",
                                    "type": "tweet",
                                    "created": "Sun, 04 Sep 2022 00:02:10 GMT",
                                    "tweetId": "1566215003996299268",
                                    "urltweet": "https://twitter.com/sillygwailo/status/1566215003996299268",
                                    "inReplyToId": "1566214791026589697",
                                    "tweetUserName": "sillygwailo"
                                },
                                {
                                    "text": "Not boring: Bullpen games, specifically the ones where a reliever starts a game, and the team purposely puts in each pitcher for no more than a few innings. It’s more democratic that way. <a href=\"https://t.co/uXM5JMHXzI\">[link]</a>",
                                    "rawText": "Not boring: Bullpen games, specifically the ones where a reliever starts a game, and the team purposely puts in each pitcher for no more than a few innings. It’s more democratic that way. https://t.co/uXM5JMHXzI",
                                    "type": "tweet",
                                    "created": "Sat, 03 Sep 2022 23:56:54 GMT",
                                    "tweetId": "1566213678961246209",
                                    "urltweet": "https://twitter.com/sillygwailo/status/1566213678961246209",
                                    "inReplyToId": "1545969711229411329",
                                    "tweetUserName": "sillygwailo"
                                },
                                {
                                    "text": "Oops, I got two beers deep for movie night tonight, which was cancelled. That means I'll do an “ask me anything” to pass the time.",
                                    "rawText": "Oops, I got two beers deep for movie night tonight, which was cancelled. That means I'll do an “ask me anything” to pass the time.",
                                    "type": "tweet",
                                    "created": "Sat, 03 Sep 2022 23:24:33 GMT",
                                    "tweetId": "1566205539612348420",
                                    "urltweet": "https://twitter.com/sillygwailo/status/1566205539612348420",
                                    "tweetUserName": "sillygwailo"
                                },
                                {
                                    "text": "Just north of 192 Cottingham St. is the site of a microconfluence. <a href=\"https://t.co/oG78rmNNJX\">[link]</a>",
                                    "rawText": "Just north of 192 Cottingham St. is the site of a microconfluence. https://t.co/oG78rmNNJX",
                                    "type": "tweet",
                                    "created": "Sat, 03 Sep 2022 19:33:58 GMT",
                                    "tweetId": "1566147507448594435",
                                    "urltweet": "https://twitter.com/sillygwailo/status/1566147507448594435",
                                    "tweetUserName": "sillygwailo"
                                },
                                {
                                    "text": "Good. <a href=\"https://t.co/294o8Bb4tQ\">[link]</a>",
                                    "rawText": "Good. https://t.co/294o8Bb4tQ",
                                    "type": "tweet",
                                    "created": "Sat, 03 Sep 2022 16:45:01 GMT",
                                    "tweetId": "1566104989864542214",
                                    "urltweet": "https://twitter.com/sillygwailo/status/1566104989864542214",
                                    "inReplyToId": "1516386135072808960",
                                    "tweetUserName": "sillygwailo"
                                },
                                {
                                    "text": "@collegeboy75 @dailysimpsons Because of this scene, I say that to myself every time I have to do something intricate but which I know I’m going to screw up.",
                                    "rawText": "@collegeboy75 @dailysimpsons Because of this scene, I say that to myself every time I have to do something intricate but which I know I’m going to screw up.",
                                    "type": "tweet",
                                    "created": "Sat, 03 Sep 2022 14:14:13 GMT",
                                    "tweetId": "1566067040678551552",
                                    "urltweet": "https://twitter.com/sillygwailo/status/1566067040678551552",
                                    "inReplyToId": "1566066587916013573",
                                    "tweetUserName": "sillygwailo"
                                },
                                {
                                    "text": "@dailysimpsons “Look under the frame, Brad.” I love that line so much.",
                                    "rawText": "@dailysimpsons “Look under the frame, Brad.” I love that line so much.",
                                    "type": "tweet",
                                    "created": "Sat, 03 Sep 2022 14:12:51 GMT",
                                    "tweetId": "1566066699601956864",
                                    "urltweet": "https://twitter.com/sillygwailo/status/1566066699601956864",
                                    "inReplyToId": "1566058618776158209",
                                    "tweetUserName": "sillygwailo"
                                },
                                {
                                    "text": "The greatest athlete of all time. <a href=\"https://t.co/3jb4lz9yu5\">[link]</a>",
                                    "rawText": "The greatest athlete of all time. https://t.co/3jb4lz9yu5",
                                    "type": "tweet",
                                    "created": "Sat, 03 Sep 2022 04:12:04 GMT",
                                    "tweetId": "1565915503851454465",
                                    "urltweet": "https://twitter.com/sillygwailo/status/1565915503851454465",
                                    "tweetUserName": "sillygwailo"
                                }
                            ]
                        },
                        {
                            "text": "September 2",
                            "type": "calendarDay",
                            "name": "02",
                            "subs": [
                                {
                                    "text": "Tonight. <a href=\"https://t.co/CojRjTxdPU\">[link]</a>",
                                    "rawText": "Tonight. https://t.co/CojRjTxdPU",
                                    "type": "tweet",
                                    "created": "Sat, 03 Sep 2022 00:25:07 GMT",
                                    "tweetId": "1565858393058951169",
                                    "urltweet": "https://twitter.com/sillygwailo/status/1565858393058951169",
                                    "tweetUserName": "sillygwailo",
                                    "subs": [
                                        {
                                            "text": "I’m not the only ungroomed white man over 40 here.",
                                            "rawText": "I’m not the only ungroomed white man over 40 here.",
                                            "type": "tweet",
                                            "created": "Sat, 03 Sep 2022 00:28:00 GMT",
                                            "tweetId": "1565859119206207488",
                                            "urltweet": "https://twitter.com/sillygwailo/status/1565859119206207488",
                                            "inReplyToId": "1565858393058951169",
                                            "tweetUserName": "sillygwailo",
                                            "subs": [
                                                {
                                                    "text": "The woman at the merch table didn’t know what Interac was. She must not be Canadian.",
                                                    "rawText": "The woman at the merch table didn’t know what Interac was. She must not be Canadian.",
                                                    "type": "tweet",
                                                    "created": "Sat, 03 Sep 2022 00:31:49 GMT",
                                                    "tweetId": "1565860076518244352",
                                                    "urltweet": "https://twitter.com/sillygwailo/status/1565860076518244352",
                                                    "inReplyToId": "1565859119206207488",
                                                    "tweetUserName": "sillygwailo",
                                                    "subs": [
                                                        {
                                                            "text": "This is the first concert where I’ve seen abortion advice and Naxalone kits at the merch table. It was on the opening act’s side.",
                                                            "rawText": "This is the first concert where I’ve seen abortion advice and Naxalone kits at the merch table. It was on the opening act’s side.",
                                                            "type": "tweet",
                                                            "created": "Sat, 03 Sep 2022 00:31:49 GMT",
                                                            "tweetId": "1565860078120566786",
                                                            "urltweet": "https://twitter.com/sillygwailo/status/1565860078120566786",
                                                            "inReplyToId": "1565860076518244352",
                                                            "tweetUserName": "sillygwailo"
                                                        }
                                                    ]
                                                }
                                            ]
                                        },
                                        {
                                            "text": "I wouldn’t call myself the biggest Animal Collective fan, but three songs in, and they justified my last-minute decision to attend their show. They’re very cool live.",
                                            "rawText": "I wouldn’t call myself the biggest Animal Collective fan, but three songs in, and they justified my last-minute decision to attend their show. They’re very cool live.",
                                            "type": "tweet",
                                            "created": "Sat, 03 Sep 2022 01:18:49 GMT",
                                            "tweetId": "1565871906964017153",
                                            "urltweet": "https://twitter.com/sillygwailo/status/1565871906964017153",
                                            "inReplyToId": "1565858393058951169",
                                            "tweetUserName": "sillygwailo"
                                        },
                                        {
                                            "text": "“Consider the Balcony Seats the Next Time You Attend a Concert at the Danforth Music Hall” will be my title of my next post on my Substack.",
                                            "rawText": "“Consider the Balcony Seats the Next Time You Attend a Concert at the Danforth Music Hall” will be my title of my next post on my Substack.",
                                            "type": "tweet",
                                            "created": "Sat, 03 Sep 2022 02:23:45 GMT",
                                            "tweetId": "1565888247435329536",
                                            "urltweet": "https://twitter.com/sillygwailo/status/1565888247435329536",
                                            "inReplyToId": "1565858393058951169",
                                            "tweetUserName": "sillygwailo"
                                        }
                                    ]
                                },
                                {
                                    "text": "I’ve been thinking about this all day. <a href=\"https://t.co/9I1mm5Wvfs\">[link]</a>",
                                    "rawText": "I’ve been thinking about this all day. https://t.co/9I1mm5Wvfs",
                                    "type": "tweet",
                                    "created": "Fri, 02 Sep 2022 21:25:35 GMT",
                                    "tweetId": "1565813212074938368",
                                    "urltweet": "https://twitter.com/sillygwailo/status/1565813212074938368",
                                    "tweetUserName": "sillygwailo"
                                },
                                {
                                    "text": "It wasn’t me, but the idea did occur to me. <a href=\"https://t.co/s1APYw8SMl\">[link]</a>",
                                    "rawText": "It wasn’t me, but the idea did occur to me. https://t.co/s1APYw8SMl",
                                    "type": "tweet",
                                    "created": "Fri, 02 Sep 2022 17:36:26 GMT",
                                    "tweetId": "1565755544568217603",
                                    "urltweet": "https://twitter.com/sillygwailo/status/1565755544568217603",
                                    "tweetUserName": "sillygwailo",
                                    "subs": [
                                        {
                                            "text": "In a previous life, in a case of mistaken identity, a woman did contact me because of what she saw on a website of mine, and we did go on to have a long-term relationship. The conditions are not right for that lightning bolt to strike again.",
                                            "rawText": "In a previous life, in a case of mistaken identity, a woman did contact me because of what she saw on a website of mine, and we did go on to have a long-term relationship. The conditions are not right for that lightning bolt to strike again.",
                                            "type": "tweet",
                                            "created": "Fri, 02 Sep 2022 17:41:38 GMT",
                                            "tweetId": "1565756853396586496",
                                            "urltweet": "https://twitter.com/sillygwailo/status/1565756853396586496",
                                            "inReplyToId": "1565755544568217603",
                                            "tweetUserName": "sillygwailo"
                                        }
                                    ]
                                },
                                {
                                    "text": "So far, 2022 is flying by. <a href=\"https://t.co/JihWX502YS\">[link]</a>",
                                    "rawText": "So far, 2022 is flying by. https://t.co/JihWX502YS",
                                    "type": "tweet",
                                    "created": "Fri, 02 Sep 2022 14:23:54 GMT",
                                    "tweetId": "1565707090714394624",
                                    "urltweet": "https://twitter.com/sillygwailo/status/1565707090714394624",
                                    "inReplyToId": "1544532759078658049",
                                    "tweetUserName": "sillygwailo"
                                }
                            ]
                        },
                        {
                            "text": "September 1",
                            "type": "calendarDay",
                            "name": "01",
                            "subs": [
                                {
                                    "text": "<a href=\"https://t.co/lQQAWJZFYE\">[link]</a>",
                                    "rawText": "https://t.co/lQQAWJZFYE",
                                    "type": "tweet",
                                    "created": "Fri, 02 Sep 2022 02:23:10 GMT",
                                    "tweetId": "1565525710571290625",
                                    "urltweet": "https://twitter.com/sillygwailo/status/1565525710571290625",
                                    "inReplyToId": "1537281362142453760",
                                    "tweetUserName": "sillygwailo"
                                },
                                {
                                    "text": "@rcousine Update to that thread: <a href=\"https://t.co/ryLbGHTyTi\">[link]</a>",
                                    "rawText": "@rcousine Update to that thread: https://t.co/ryLbGHTyTi",
                                    "type": "tweet",
                                    "created": "Fri, 02 Sep 2022 00:47:13 GMT",
                                    "tweetId": "1565501564642799616",
                                    "urltweet": "https://twitter.com/sillygwailo/status/1565501564642799616",
                                    "inReplyToId": "1565499805409112065",
                                    "tweetUserName": "sillygwailo"
                                },
                                {
                                    "text": "Now that’s what I would call a positive sign! <a href=\"https://t.co/ZiMVV5TqG6\">[link]</a>",
                                    "rawText": "Now that’s what I would call a positive sign! https://t.co/ZiMVV5TqG6",
                                    "type": "tweet",
                                    "created": "Fri, 02 Sep 2022 00:04:37 GMT",
                                    "tweetId": "1565490846430101505",
                                    "urltweet": "https://twitter.com/sillygwailo/status/1565490846430101505",
                                    "inReplyToId": "1565024498600091650",
                                    "tweetUserName": "sillygwailo"
                                },
                                {
                                    "text": "I got a geo-targeted ad in podcast recently, and I have a pretty good idea of how it was done. I rarely listen to podcasts, and this makes me want to listen to them even less.",
                                    "rawText": "I got a geo-targeted ad in podcast recently, and I have a pretty good idea of how it was done. I rarely listen to podcasts, and this makes me want to listen to them even less.",
                                    "type": "tweet",
                                    "created": "Thu, 01 Sep 2022 22:56:12 GMT",
                                    "tweetId": "1565473627520253952",
                                    "urltweet": "https://twitter.com/sillygwailo/status/1565473627520253952",
                                    "tweetUserName": "sillygwailo"
                                },
                                {
                                    "text": "I don’t know what I did to deserve it, but a woman looked me right in the eyes today.",
                                    "rawText": "I don’t know what I did to deserve it, but a woman looked me right in the eyes today.",
                                    "type": "tweet",
                                    "created": "Thu, 01 Sep 2022 21:51:19 GMT",
                                    "tweetId": "1565457297731633152",
                                    "urltweet": "https://twitter.com/sillygwailo/status/1565457297731633152",
                                    "tweetUserName": "sillygwailo"
                                },
                                {
                                    "text": "How do I mute the “‘accidentally’ tweeting a single word” meme?",
                                    "rawText": "How do I mute the “‘accidentally’ tweeting a single word” meme?",
                                    "type": "tweet",
                                    "created": "Thu, 01 Sep 2022 20:10:03 GMT",
                                    "tweetId": "1565431814126280709",
                                    "urltweet": "https://twitter.com/sillygwailo/status/1565431814126280709",
                                    "tweetUserName": "sillygwailo"
                                },
                                {
                                    "text": "I want the job of bossing people around with a megaphone while sitting on a high chair, but it looks like that one’s taken. <a href=\"https://t.co/5aMfgPuSZI\">[link]</a>",
                                    "rawText": "I want the job of bossing people around with a megaphone while sitting on a high chair, but it looks like that one’s taken. https://t.co/5aMfgPuSZI",
                                    "type": "tweet",
                                    "created": "Thu, 01 Sep 2022 17:21:23 GMT",
                                    "tweetId": "1565389368856133632",
                                    "urltweet": "https://twitter.com/sillygwailo/status/1565389368856133632",
                                    "tweetUserName": "sillygwailo"
                                },
                                {
                                    "text": "Whenever someone on a video call wears an all-green shirt, I mentally fill in the area of their shirt with their background (real or virtual). And then the wallpaper scene from Garden State comes to mind. <a href=\"https://t.co/h5FrOCj6FS\">[link]</a>",
                                    "rawText": "Whenever someone on a video call wears an all-green shirt, I mentally fill in the area of their shirt with their background (real or virtual). And then the wallpaper scene from Garden State comes to mind. https://t.co/h5FrOCj6FS",
                                    "type": "tweet",
                                    "created": "Thu, 01 Sep 2022 17:17:32 GMT",
                                    "tweetId": "1565388397362946056",
                                    "urltweet": "https://twitter.com/sillygwailo/status/1565388397362946056",
                                    "tweetUserName": "sillygwailo"
                                },
                                {
                                    "text": "@rtanglao The reason I looked up the boy choy pattern was because I saw someone wearing a Hawaiian shirt with a shirt with a pineapple pattern, and I was like “Come on, that’s way too obvious!” So yes, I would love for you to wear a mapo tofu or sinigang or adobo or pancit Hawaiian shirt.",
                                    "rawText": "@rtanglao The reason I looked up the boy choy pattern was because I saw someone wearing a Hawaiian shirt with a shirt with a pineapple pattern, and I was like “Come on, that’s way too obvious!” So yes, I would love for you to wear a mapo tofu or sinigang or adobo or pancit Hawaiian shirt.",
                                    "type": "tweet",
                                    "created": "Thu, 01 Sep 2022 14:38:48 GMT",
                                    "tweetId": "1565348451961143301",
                                    "urltweet": "https://twitter.com/sillygwailo/status/1565348451961143301",
                                    "inReplyToId": "1565345182073356290",
                                    "tweetUserName": "sillygwailo"
                                },
                                {
                                    "text": "The edit button will be abused, in a way Twitter didn’t anticipate. <a href=\"https://t.co/Y34JIS1GAt\">[link]</a>",
                                    "rawText": "The edit button will be abused, in a way Twitter didn’t anticipate. https://t.co/Y34JIS1GAt",
                                    "type": "tweet",
                                    "created": "Thu, 01 Sep 2022 13:41:38 GMT",
                                    "tweetId": "1565334066790023168",
                                    "urltweet": "https://twitter.com/sillygwailo/status/1565334066790023168",
                                    "tweetUserName": "sillygwailo",
                                    "subs": [
                                        {
                                            "text": "Aujourd’hui, nous sommes tous le bouton d’édition de Twitter.",
                                            "rawText": "Aujourd’hui, nous sommes tous le bouton d’édition de Twitter.",
                                            "type": "tweet",
                                            "created": "Thu, 01 Sep 2022 14:31:03 GMT",
                                            "tweetId": "1565346500959383555",
                                            "urltweet": "https://twitter.com/sillygwailo/status/1565346500959383555",
                                            "inReplyToId": "1565334066790023168",
                                            "tweetUserName": "sillygwailo"
                                        }
                                    ]
                                },
                                {
                                    "text": "@Twitter Nobody cares. Add an edit bu—Oh.",
                                    "rawText": "@Twitter Nobody cares. Add an edit bu—Oh.",
                                    "type": "tweet",
                                    "created": "Thu, 01 Sep 2022 13:40:45 GMT",
                                    "tweetId": "1565333842004688897",
                                    "urltweet": "https://twitter.com/sillygwailo/status/1565333842004688897",
                                    "inReplyToId": "1565318587736285184",
                                    "tweetUserName": "sillygwailo"
                                }
                            ]
                        }
                    ]
                }
            ]
        }
    }
}